cityseg/SemanticSidewalk_id2label.json
cityseg/__init__.py
cityseg/config.py
cityseg/config.yaml
cityseg/exceptions.py
cityseg/file_handler.py
cityseg/main.py
cityseg/palettes.py
cityseg/pipeline.py
cityseg/processing_plan.py
cityseg/processors.py
cityseg/segmentation_analyzer.py
cityseg/utils.py
cityseg/video_file_iterator.py
cityseg/visualization_handler.py
cityseg-0.3.1rc0.dist-info/METADATA
cityseg-0.3.1rc0.dist-info/WHEEL
cityseg-0.3.1rc0.dist-info/entry_points.txt
cityseg-0.3.1rc0.dist-info/licenses/LICENSE.txt
cityseg-0.3.1rc0.dist-info/RECORD
