Metadata-Version: 2.3
Name: cityseg
Version: 0.3.1rc0
Summary: A flexible and efficient semantic segmentation pipeline for processing images and videos
Author-email: Andrew Mitchell <mitchellacoustics15@gmail.com>
License: BSD-3-Clause
License-File: LICENSE.txt
Requires-Python: >=3.10
Requires-Dist: h5py>=3.11.0
Requires-Dist: loguru>=0.7.2
Requires-Dist: numpy>=2.0.1
Requires-Dist: opencv-python>=4.10.0.84
Requires-Dist: pandas[performance]>=2.2.2
Requires-Dist: pillow>=10.4.0
Requires-Dist: pyyaml>=6.0.1
Requires-Dist: scipy>=1.14.0
Requires-Dist: torch>=2.4.0
Requires-Dist: torchvision>=0.19.0
Requires-Dist: tqdm>=4.66.4
Requires-Dist: transformers>=4.43.2
